{
  "id": "cl-p159c",
  "pick_number": "P-159c",
  "country": {
    "en": "Chile",
    "es": "Chile"
  },
  "denomination": {
    "value": 20000,
    "currency": "Pesos",
    "subtype": "",
    "alternatives": []
  },
  "year": 2008,
  "signatures": [
    "De Gregorio",
    "Zurbuchen"
  ],
  "themes": [
    "personaje:andres_bello",
    "construccion:universidad_de_chile"
  ],
  "colnect": {
    "url": "https://colnect.com/es/banknotes/banknote/91134-20000_Pesos-1997-2008_Issue-Chile",
    "group": "1997-2008 Issue"
  },
  "commemorative": false,
  "overprint": false,
  "verificado": false,
  "notes": {
    "serie": "",
    "bank": "",
    "zone": "",
    "vigencia": "1998 - 2008",
    "obs": ""
  },
  "specimens": [
    {
      "serial_number": "AB1994436",
      "condition": "VF"
    }
  ],
  "numista": "https://en.numista.com/232327"
}
