{
  "id": "np-p46a",
  "pick_number": "P-46a",
  "country": {
    "en": "Nepal",
    "es": "Nepal"
  },
  "denomination": {
    "value": 5,
    "currency": "Rupias",
    "subtype": "",
    "alternatives": []
  },
  "year": 2002,
  "signatures": [],
  "themes": [
    "rey:birendra_bir_bikram_shah",
    "construccion:templo_pagoda",
    "fauna:yaks",
    "lugar:himalayas",
    "simbolo:emblema_del_banco_central_de_nepal"
  ],
  "colnect": {
    "url": "https://colnect.com/es/banknotes/banknote/9406-5_Rupees-2002-2006_ND_King_Gyanendra_Portrait_Issue-Nepal",
    "group": ""
  },
  "commemorative": false,
  "overprint": false,
  "verificado": false,
  "notes": {
    "serie": "",
    "bank": "",
    "zone": "",
    "vigencia": "",
    "obs": ""
  },
  "specimens": [
    {
      "serial_number": "इ ०४४४३२",
      "condition": "UNC"
    }
  ]
}