{
  "id": "vn-p120h",
  "pick_number": "P-120h",
  "country": {
    "en": "Vietnam",
    "es": "Vietnam"
  },
  "denomination": {
    "value": 20000,
    "currency": "Dongs",
    "subtype": "",
    "alternatives": []
  },
  "year": 2017,
  "signatures": [],
  "themes": [
    "personaje:ho_chi_minh",
    "construccion:puente_cubierto_de_hoi_an"
  ],
  "colnect": {
    "url": "https://colnect.com/es/banknotes/banknote/94961-20000_%C4%90%E1%BB%93ng-2003-2021_Polymer_Issue-Vietnam",
    "group": ""
  },
  "commemorative": false,
  "overprint": false,
  "verificado": true,
  "notes": {
    "serie": "",
    "bank": "",
    "zone": "",
    "vigencia": "",
    "obs": ""
  },
  "specimens": [
    {
      "serial_number": "UA 17069054",
      "condition": ""
    }
  ]
}